smartshell.py
smartshell_ai-0.1.dist-info/METADATA
smartshell_ai-0.1.dist-info/WHEEL
smartshell_ai-0.1.dist-info/entry_points.txt
smartshell_ai-0.1.dist-info/top_level.txt
smartshell_ai-0.1.dist-info/RECORD
